{
  "posts": [
    {
      "id": 2,
      "title": "Siatkówka kobiet",
      "slug": "siatk-wka-kobiet",
      "excerpt": "Kiedy siatkówka kobiet",
      "content": "Wszyscy czekamy na kolejny mecz kobiet w siatkówkę. Kiedy on będzie?",
      "categories": [
        "sport"
      ]
    },
    {
      "id": 3,
      "title": "Bieg na zewnątrz czy siłownia",
      "slug": "bieg-na-zewn-trz-czy-si-ownia",
      "excerpt": "Bieganie na zewnątrz czy na bieżni?",
      "content": "Bieganie na zewnątrz czy na bieżni? Osobiście wolę biegać na zewnątrz a jakie jest wasze zdanie? Opowiem wam historię...",
      "categories": [
        "sport"
      ]
    },
    {
      "id": 4,
      "title": "Ulubione sporty według polaków",
      "slug": "ulubione-sporty-wed-ug-polak-w",
      "excerpt": "Ulubione sporty według polaków",
      "content": "Ulubione sporty według polaków to piłka nozna oraz siatkówka",
      "categories": [
        "sport"
      ]
    },
    {
      "id": 5,
      "title": "Zdrowe tłuszcze",
      "slug": "zdrowe-t-uszcze",
      "excerpt": "Awokado, łosoś, orzechy",
      "content": "Awokado, łosoś, orzechy i nie tylko to źródło zdrowych tłuszczy",
      "categories": [
        "dieta"
      ]
    },
    {
      "id": 6,
      "title": "Zbalansowana dieta ",
      "slug": "zbalansowana-dieta",
      "excerpt": "Zbalansowana dieta każdego człowieka",
      "content": "Zbalansowana dieta każdego człowieka to korzyści nie tylko dla ciała ale umysłu",
      "categories": [
        "dieta"
      ]
    },
    {
      "id": 7,
      "title": "Mięso czy warzywa?",
      "slug": "mi-so-czy-warzywa",
      "excerpt": "Mięso czy warzywa?",
      "content": "Mięso czy warzywa? Myślę że nie jedna osoba zastanawia się...",
      "categories": [
        "dieta"
      ]
    },
    {
      "id": 8,
      "title": "Wiadomości z ostatniej chwili",
      "slug": "wiadomo-ci-z-ostatniej-chwili",
      "excerpt": "Wiadomości z ostatniej chwili",
      "content": "Wiadomości z ostatniej chwili. Usa...",
      "categories": [
        "swiat"
      ]
    },
    {
      "id": 9,
      "title": "NBC",
      "slug": "nbc",
      "excerpt": "Wiadomości",
      "content": "Wiadomości NBC. Z ostatniej chwili wiadomości prosto ze stanów zjednoczonych",
      "categories": [
        "swiat"
      ]
    },
    {
      "id": 10,
      "title": "News ENG",
      "slug": "news-eng",
      "excerpt": "W języku angielskim",
      "content": "Today we are gonna talk about state of usa",
      "categories": [
        "swiat"
      ]
    },
    {
      "id": 11,
      "title": "Javascript",
      "slug": "javascript",
      "excerpt": "Best programming languages",
      "content": "Best programming languages is a hot topic",
      "categories": [
        "programowanie"
      ]
    },
    {
      "id": 12,
      "title": "React framework",
      "slug": "react-framework",
      "excerpt": "Framework react is the most used framework ",
      "content": "Framework react is the most used frontend framework ",
      "categories": [
        "programowanie"
      ]
    },
    {
      "id": 13,
      "title": "Jęzki wysokiego poziomu czy niskiego?",
      "slug": "j-zki-wysokiego-poziomu-czy-niskiego",
      "excerpt": "Jęzki wysokiego poziomu czy niskiego?",
      "content": "Jęzki wysokiego poziomu czy niskiego? Odpowiedź jest niejednoznaczna!",
      "categories": [
        "programowanie"
      ]
    }
  ]
}